papis_zotero/__init__.py
papis_zotero/bibtex.py
papis_zotero/server.py
papis_zotero/sql.py
papis_zotero/utils.py
papis_zotero-0.2.dist-info/METADATA
papis_zotero-0.2.dist-info/WHEEL
papis_zotero-0.2.dist-info/entry_points.txt
papis_zotero-0.2.dist-info/licenses/LICENSE
papis_zotero-0.2.dist-info/RECORD
