Metadata-Version: 2.4
Name: papis-zotero
Version: 0.2
Summary: Interact with Zotero using papis
Project-URL: Repository, https://github.com/papis/papis-zotero
Author-email: Alejandro Gallo <aamsgallo@gmail.com>
Maintainer-email: Alejandro Gallo <aamsgallo@gmail.com>
License: GPL-3.0-or-later
License-File: LICENSE
Keywords: bibtex,biliography,cli,management,papis,zotero
Classifier: Environment :: Console
Classifier: Environment :: Console :: Curses
Classifier: Intended Audience :: Developers
Classifier: Intended Audience :: Education
Classifier: Intended Audience :: Science/Research
Classifier: Intended Audience :: System Administrators
Classifier: License :: OSI Approved :: GNU General Public License v3 (GPLv3)
Classifier: Operating System :: MacOS
Classifier: Operating System :: Microsoft
Classifier: Operating System :: OS Independent
Classifier: Operating System :: POSIX
Classifier: Operating System :: Unix
Classifier: Programming Language :: Python :: 3 :: Only
Classifier: Programming Language :: Python :: 3.8
Classifier: Programming Language :: Python :: 3.9
Classifier: Programming Language :: Python :: 3.10
Classifier: Programming Language :: Python :: 3.11
Classifier: Programming Language :: Python :: 3.12
Classifier: Programming Language :: Python :: 3.13
Classifier: Topic :: Utilities
Requires-Python: >=3.8
Requires-Dist: papis<0.15,>=0.14
Provides-Extra: develop
Requires-Dist: mypy>=0.7; extra == 'develop'
Requires-Dist: pytest; extra == 'develop'
Requires-Dist: pytest-cov; extra == 'develop'
Requires-Dist: ruff; extra == 'develop'
Requires-Dist: types-pyyaml; extra == 'develop'
